seqrepo_rest_service/__init__.py
seqrepo_rest_service/__main__.py
seqrepo_rest_service/cli.py
seqrepo_rest_service/threadglobals.py
seqrepo_rest_service/utils.py
seqrepo_rest_service/refget/__init__.py
seqrepo_rest_service/refget/refget-openapi.yaml
seqrepo_rest_service/refget/routes/__init__.py
seqrepo_rest_service/refget/routes/metadata.py
seqrepo_rest_service/refget/routes/ping.py
seqrepo_rest_service/refget/routes/sequence.py
seqrepo_rest_service/refget/routes/serviceInfo.py
seqrepo_rest_service/seqrepo/__init__.py
seqrepo_rest_service/seqrepo/openapi.yaml
seqrepo_rest_service/seqrepo/routes/__init__.py
seqrepo_rest_service/seqrepo/routes/metadata.py
seqrepo_rest_service/seqrepo/routes/ping.py
seqrepo_rest_service/seqrepo/routes/sequence.py
seqrepo_rest_service-0.2.2.dist-info/LICENSE
seqrepo_rest_service-0.2.2.dist-info/METADATA
seqrepo_rest_service-0.2.2.dist-info/WHEEL
seqrepo_rest_service-0.2.2.dist-info/entry_points.txt
seqrepo_rest_service-0.2.2.dist-info/top_level.txt
seqrepo_rest_service-0.2.2.dist-info/zip-safe
seqrepo_rest_service-0.2.2.dist-info/RECORD
