Metadata-Version: 2.1
Name: seqrepo-rest-service
Version: 0.2.2
Summary: SeqRepo REST Service
Author-email: biocommons contributors <biocommons-dev@googlegroups.com>
Project-URL: Homepage, https://github.com/biocommons/seqrepo-rest-service
Project-URL: Bug Tracker, https://github.com/biocommons/seqrepo-rest-service/issues
Classifier: Programming Language :: Python :: 3
Classifier: Programming Language :: Python :: 3.9
Classifier: Programming Language :: Python :: 3.10
Classifier: Programming Language :: Python :: 3.11
Classifier: License :: OSI Approved :: MIT License
Classifier: Operating System :: OS Independent
Requires-Python: >=3.9
License-File: LICENSE
Requires-Dist: biocommons.seqrepo ~=0.6
Requires-Dist: coloredlogs
Requires-Dist: connexion[swagger-ui] ~=2.2
Requires-Dist: Flask ~=2.2
Provides-Extra: dev
Requires-Dist: bandit ~=1.7 ; extra == 'dev'
Requires-Dist: black ~=22.3 ; extra == 'dev'
Requires-Dist: build ~=0.8 ; extra == 'dev'
Requires-Dist: flake8 ~=4.0 ; extra == 'dev'
Requires-Dist: ipython ~=8.4 ; extra == 'dev'
Requires-Dist: isort ~=5.10 ; extra == 'dev'
Requires-Dist: mypy ; extra == 'dev'
Requires-Dist: pylint ~=2.14 ; extra == 'dev'
Requires-Dist: pytest-cov ~=4.1 ; extra == 'dev'
Requires-Dist: pytest-optional-tests ; extra == 'dev'
Requires-Dist: pytest ~=7.1 ; extra == 'dev'
Requires-Dist: wheel ; extra == 'dev'
Requires-Dist: vcrpy ; extra == 'dev'
Provides-Extra: docs
Requires-Dist: mkdocs ; extra == 'docs'
